{"State = 0": ["Orbitals occupied by up: [0]", "Orbitals occupied by down: [0]", "Energy of occupied orbitals: [0.0199, 0.0199]", "Total energy = 0.0398"], "State = 1": ["Orbitals occupied by up: [0]", "Orbitals occupied by down: [1]", "Energy of occupied orbitals: [0.0199, 0.0794]", "Total energy = 0.0993"], "State = 2": ["Orbitals occupied by up: [1]", "Orbitals occupied by down: [0]", "Energy of occupied orbitals: [0.0794, 0.0199]", "Total energy = 0.0993"], "State = 3": ["Orbitals occupied by up: [1]", "Orbitals occupied by down: [1]", "Energy of occupied orbitals: [0.0794, 0.0794]", "Total energy = 0.1588"], "State = 4": ["Orbitals occupied by up: [0]", "Orbitals occupied by down: [2]", "Energy of occupied orbitals: [0.0199, 0.1787]", "Total energy = 0.1986"], "State = 5": ["Orbitals occupied by up: [2]", "Orbitals occupied by down: [0]", "Energy of occupied orbitals: [0.1787, 0.0199]", "Total energy = 0.1986"], "State = 6": ["Orbitals occupied by up: [1]", "Orbitals occupied by down: [2]", "Energy of occupied orbitals: [0.0794, 0.1787]", "Total energy = 0.2581"], "State = 7": ["Orbitals occupied by up: [1]", "Orbitals occupied by down: [2]", "Energy of occupied orbitals: [0.0794, 0.1787]", "Total energy = 0.2581"], "State = 8": ["Orbitals occupied by up: [0]", "Orbitals occupied by down: [3]", "Energy of occupied orbitals: [0.0199, 0.3177]", "Total energy = 0.3376"], "State = 9": ["Orbitals occupied by up: [0]", "Orbitals occupied by down: [3]", "Energy of occupied orbitals: [0.0199, 0.3177]", "Total energy = 0.3376"]}